uni_translate/__init__.py
uni_translate/cli.py
uni_translate-0.0.5.dist-info/LICENSE
uni_translate-0.0.5.dist-info/METADATA
uni_translate-0.0.5.dist-info/WHEEL
uni_translate-0.0.5.dist-info/entry_points.txt
uni_translate-0.0.5.dist-info/top_level.txt
uni_translate-0.0.5.dist-info/RECORD
