Metadata-Version: 2.1
Name: uni-translate
Version: 0.0.5
Summary: Python library to "translate" a variety of unicode special characters to normal text
Home-page: https://github.com/anytarseir67/uni-translate
Author: anytarseir67
License: GPLv3
Platform: UNKNOWN
License-File: LICENSE
